chaoszos/__init__.py
chaoszos/__send_zos_command.py
chaoszos/setup.py
chaoszos/zos/__init__.py
chaoszos/zos/actions.py
chaoszos/zos/probes.py
chaostoolkit_zos-0.3.0.dist-info/LICENSE
chaostoolkit_zos-0.3.0.dist-info/METADATA
chaostoolkit_zos-0.3.0.dist-info/WHEEL
chaostoolkit_zos-0.3.0.dist-info/top_level.txt
chaostoolkit_zos-0.3.0.dist-info/RECORD
