Metadata-Version: 2.1
Name: chaostoolkit-zos
Version: 0.3.0
Summary: Chaos Toolkit Extension for z/OS
Home-page: http://chaostoolkit.org
Author: Kevin McKenzie
Author-email: kmckenzi@us.ibm.com
License: Apache License Version 2.0
Classifier: Development Status :: 2 - Pre-Alpha
Classifier: Intended Audience :: Developers
Classifier: License :: Freely Distributable
Classifier: Operating System :: OS Independent
Classifier: License :: OSI Approved :: Apache Software License
Classifier: Programming Language :: Python
Classifier: Programming Language :: Python :: 3
Classifier: Programming Language :: Python :: 3.7
Classifier: Programming Language :: Python :: 3.8
Classifier: Programming Language :: Python :: 3.9
Classifier: Programming Language :: Python :: Implementation
Classifier: Programming Language :: Python :: Implementation :: CPython
Requires-Python: >=3.7.*
License-File: LICENSE
Requires-Dist: chaostoolkit-lib (>=1.22.1)
Requires-Dist: zos-utilities (>=0.5.0)
Requires-Dist: requests
Requires-Dist: paramiko
Requires-Dist: zhmcclient
